LICENSE
README.md
setup.py
primenote/__db__.py
primenote/__id__.py
primenote/__init__.py
primenote/main.py
primenote.egg-info/PKG-INFO
primenote.egg-info/SOURCES.txt
primenote.egg-info/dependency_links.txt
primenote.egg-info/entry_points.txt
primenote.egg-info/requires.txt
primenote.egg-info/top_level.txt
primenote/backend/__init__.py
primenote/backend/cli.py
primenote/backend/cryptography.py
primenote/backend/database.py
primenote/backend/legacy.py
primenote/backend/logger.py
primenote/backend/observer.py
primenote/menus/__init__.py
primenote/menus/bars.py
primenote/menus/core.py
primenote/menus/note.py
primenote/menus/search.py
primenote/notes/__init__.py
primenote/notes/console.py
primenote/notes/html.py
primenote/notes/image.py
primenote/notes/plain.py
primenote/notes/text.py
primenote/notes/vim.py
primenote/plugins/__init__.py
primenote/plugins/antidote/__init__.py
primenote/plugins/antidote/com.py
primenote/plugins/antidote/dbus.py
primenote/settings/__init__.py
primenote/settings/about.py
primenote/settings/advanced.py
primenote/settings/base.py
primenote/settings/general.py
primenote/settings/hotkeys.py
primenote/settings/logs.py
primenote/settings/menus.py
primenote/settings/mouse.py
primenote/settings/plugins.py
primenote/settings/profile.py
primenote/settings/reset.py
primenote/settings/wizard.py
primenote/ui/__init__.py
primenote/ui/global.css
primenote/ui/fonts/LiberationMono-Bold.ttf
primenote/ui/fonts/LiberationMono-BoldItalic.ttf
primenote/ui/fonts/LiberationMono-Italic.ttf
primenote/ui/fonts/LiberationMono-Regular.ttf
primenote/ui/icons/activate.svg
primenote/ui/icons/add.svg
primenote/ui/icons/antidote_corrector.svg
primenote/ui/icons/antidote_dictionnary.svg
primenote/ui/icons/antidote_guide.svg
primenote/ui/icons/aspect_ratio.svg
primenote/ui/icons/assistant_add.svg
primenote/ui/icons/assistant_menu.svg
primenote/ui/icons/assistant_toggle.svg
primenote/ui/icons/bold.svg
primenote/ui/icons/capitalize.svg
primenote/ui/icons/clear_format.svg
primenote/ui/icons/console.svg
primenote/ui/icons/console_regular.svg
primenote/ui/icons/console_starred.svg
primenote/ui/icons/copy.svg
primenote/ui/icons/credits
primenote/ui/icons/crop.svg
