Metadata-Version: 2.1
Name: primenote
Version: 1.5.3
Summary: Fanciest sticky note-taking application. Now with Vim!
Home-page: https://gitlab.com/william.belanger/primenote
Author: William Belanger
Keywords: sticky note plain rich text vim css pyqt qt
Platform: Linux
Classifier: License :: OSI Approved :: GNU General Public License v3 (GPLv3)
Classifier: Programming Language :: Python :: 3.6
Classifier: Operating System :: POSIX :: Linux
License-File: LICENSE
Requires-Dist: pyqt5
Requires-Dist: requests
Requires-Dist: cryptography
